dumbPaintTool/__init__.py
dumbPaintTool/__main__.py
dumbPaintTool/app/__init__.py
dumbPaintTool/app/about.py
dumbPaintTool/app/canvaslayer.py
dumbPaintTool/app/cfg.py
dumbPaintTool/app/const.py
dumbPaintTool/app/exportarea.py
dumbPaintTool/app/glbls.py
dumbPaintTool/app/importimage.py
dumbPaintTool/app/layersctrl.py
dumbPaintTool/app/main.py
dumbPaintTool/app/maintemplate.py
dumbPaintTool/app/paintarea.py
dumbPaintTool/app/painttoolkit.py
dumbPaintTool/app/palette.py
dumbPaintTool/app/textarea.py
dumbPaintTool/app/toolspanel.py
dumbPaintTool/app/filters/__init__.py
dumbPaintTool/app/filters/brightness_contrast.py
dumbPaintTool/app/filters/hue_chroma_lightness.py
dumbPaintTool/app/state/__init__.py
dumbPaintTool/app/state/brush.py
dumbPaintTool/app/state/layers.py
dumbPaintTool/tui/paintToolKit.tui.json
dumbPaintTool/tui/quickImport.tui.json
dumbPaintTool/tui/tools.tui.json
dumbpainttool-0.48.2a0.dist-info/METADATA
dumbpainttool-0.48.2a0.dist-info/WHEEL
dumbpainttool-0.48.2a0.dist-info/entry_points.txt
dumbpainttool-0.48.2a0.dist-info/top_level.txt
dumbpainttool-0.48.2a0.dist-info/RECORD
