Metadata-Version: 2.4
Name: dumbPaintTool
Version: 0.48.2a0
Summary: the Dumb Paint Tool is THE Terminal ASCII Photoshop
Author-email: Eugenio Parodi <ceccopierangiolieugenio@googlemail.com>
Project-URL: Homepage, https://github.com/ceccopierangiolieugenio/pyTermTk/tree/main/apps/dumbPaintTool
Project-URL: Repository, https://github.com/ceccopierangiolieugenio/pyTermTk.git
Project-URL: Issues, https://github.com/ceccopierangiolieugenio/pyTermTk/issues
Project-URL: Changelog, https://github.com/ceccopierangiolieugenio/pyTermTk/blob/main/apps/dumbPaintTool/CHANGELOG.md
Classifier: Programming Language :: Python :: 3
Classifier: License :: OSI Approved :: MIT License
Classifier: Operating System :: OS Independent
Classifier: Development Status :: 3 - Alpha
Classifier: Environment :: Console
Classifier: Intended Audience :: Education
Classifier: Intended Audience :: Developers
Classifier: Intended Audience :: Information Technology
Classifier: Topic :: Terminals
Classifier: Topic :: Text Editors :: Text Processing
Classifier: Topic :: Multimedia :: Graphics
Classifier: Topic :: Multimedia :: Graphics :: Editors
Classifier: Topic :: Multimedia :: Graphics :: Editors :: Raster-Based
Classifier: Topic :: Multimedia :: Graphics :: Graphics Conversion
Classifier: Topic :: Software Development :: User Interfaces
Classifier: Topic :: Software Development :: Libraries
Classifier: Topic :: Software Development :: Libraries :: Python Modules
Classifier: Topic :: Software Development :: Libraries :: Application Frameworks
Requires-Python: >=3.9
Requires-Dist: pyTermTk>=0.49.0-a0
Requires-Dist: pyperclip
Requires-Dist: Pillow
